carball/__init__.py
carball/decompile_replays.py
carball/analysis/PROTOBUF_VERSION
carball/analysis/__init__.py
carball/analysis/analysis_manager.py
carball/analysis/cleaner/__init__.py
carball/analysis/cleaner/cleaner.py
carball/analysis/cleaner/frame_cleaner.py
carball/analysis/constants/__init__.py
carball/analysis/constants/basic_math.py
carball/analysis/constants/field_constants.py
carball/analysis/constants/playlist.py
carball/analysis/hit_detection/__init__.py
carball/analysis/hit_detection/base_hit.py
carball/analysis/hit_detection/hit_analysis.py
"carball/analysis/hit_detection/hitbox/Vehicle Specifications v1.39 - Hitboxes, Handling.xlsx"
carball/analysis/hit_detection/hitbox/__init__.py
carball/analysis/hit_detection/hitbox/car.py
carball/analysis/hit_detection/hitbox/hitbox.py
carball/analysis/saltie_game/__init__.py
carball/analysis/saltie_game/saltie_game.py
carball/analysis/saltie_game/metadata/ApiDemo.py
carball/analysis/saltie_game/metadata/ApiGame.py
carball/analysis/saltie_game/metadata/ApiGoal.py
carball/analysis/saltie_game/metadata/ApiMutators.py
carball/analysis/saltie_game/metadata/ApiPlayer.py
carball/analysis/saltie_game/metadata/ApiPlayerCameraSettings.py
carball/analysis/saltie_game/metadata/ApiPlayerLoadout.py
carball/analysis/saltie_game/metadata/ApiTeam.py
carball/analysis/saltie_game/metadata/__init__.py
carball/analysis/simulator/__init__.py
carball/analysis/simulator/ball_simulator.py
carball/analysis/simulator/bounce.py
carball/analysis/simulator/map_constants.py
carball/analysis/stats/__init__.py
carball/analysis/stats/stats.py
carball/analysis/stats/stats_list.py
carball/analysis/stats/stats_manager.py
carball/analysis/stats/ball_forward/__init__.py
carball/analysis/stats/ball_forward/distance_hit_ball_forward.py
carball/analysis/stats/boost/__init__.py
carball/analysis/stats/boost/boost.py
carball/analysis/stats/controls/__init__.py
carball/analysis/stats/controls/controls.py
carball/analysis/stats/possession/__init__.py
carball-0.6.15.dist-info/LICENSE
carball-0.6.15.dist-info/METADATA
carball-0.6.15.dist-info/NOTICE
carball-0.6.15.dist-info/WHEEL
carball-0.6.15.dist-info/top_level.txt
carball-0.6.15.dist-info/RECORD
