Metadata-Version: 2.1
Name: carball
Version: 0.6.15
Summary: Rocket League replay parsing and analysis.
Home-page: https://github.com/SaltieRL/carball
Author: Matthew Mage, Harry Xie, David Turner
Author-email: sciguymjm@gmail.com
License: Apache 2.0
Keywords: rocket-league
Platform: UNKNOWN
Requires-Dist: pandas (==0.24.2)
Requires-Dist: protobuf (==3.6.1)
Requires-Dist: xlrd
